{
    "GMTUSDT": {
        "price": 0.0709,
        "time": "2025-02-13T13:46:21.359625",
        "tp1_hit": false,
        "tp1_price": null
    },
    "USDCUSDT": {
        "price": 0.9999,
        "time": "2025-02-13T14:46:22.549329",
        "tp1_hit": false,
        "tp1_price": null
    },
    "TRUMPUSDT": {
        "price": 16.69,
        "time": "2025-02-13T15:35:46.760524",
        "tp1_hit": false,
        "tp1_price": null
    },
    "ADAUSDT": {
        "price": 0.7835,
        "time": "2025-02-13T15:35:49.274594",
        "tp1_hit": false,
        "tp1_price": null
    },
    "ENAUSDT": {
        "price": 0.4606,
        "time": "2025-02-13T15:35:50.101252",
        "tp1_hit": false,
        "tp1_price": null
    },
    "XRPUSDT": {
        "price": 2.4536,
        "time": "2025-02-13T15:46:13.507124",
        "tp1_hit": false,
        "tp1_price": null
    },
    "DOTUSDT": {
        "price": 5.186,
        "time": "2025-02-13T15:46:18.404703",
        "tp1_hit": false,
        "tp1_price": null
    }
}